xpag/__init__.py
xpag/agents/__init__.py
xpag/agents/agent.py
xpag/agents/all_agents.py
xpag/agents/flax_agents/__init__.py
xpag/agents/flax_agents/sac/__init__.py
xpag/agents/flax_agents/sac/sac.py
xpag/agents/flax_agents/sac/sac_from_jaxrl.py
xpag/agents/flax_agents/sdqn/__init__.py
xpag/agents/flax_agents/sdqn/sdqn.py
xpag/agents/flax_agents/td3/__init__.py
xpag/agents/flax_agents/td3/td3.py
xpag/agents/flax_agents/tqc/__init__.py
xpag/agents/flax_agents/tqc/tqc.py
xpag/agents/rljax_agents/__init__.py
xpag/agents/rljax_agents/rljax_interface.py
xpag/agents/rljax_agents/algorithm/__init__.py
xpag/agents/rljax_agents/algorithm/ddpg.py
xpag/agents/rljax_agents/algorithm/sac.py
xpag/agents/rljax_agents/algorithm/sac_discor.py
xpag/agents/rljax_agents/algorithm/td3.py
xpag/agents/rljax_agents/algorithm/tqc.py
xpag/agents/rljax_agents/algorithm/base_class/__init__.py
xpag/agents/rljax_agents/algorithm/base_class/actor_critic.py
xpag/agents/rljax_agents/algorithm/base_class/base_algorithm.py
xpag/agents/rljax_agents/algorithm/misc/__init__.py
xpag/agents/rljax_agents/algorithm/misc/discor_mixin.py
xpag/agents/rljax_agents/network/__init__.py
xpag/agents/rljax_agents/network/actor.py
xpag/agents/rljax_agents/network/base.py
xpag/agents/rljax_agents/network/critic.py
xpag/agents/rljax_agents/network/initializer.py
xpag/agents/rljax_agents/util/__init__.py
xpag/agents/rljax_agents/util/distribution.py
xpag/agents/rljax_agents/util/input.py
xpag/agents/rljax_agents/util/loss.py
xpag/agents/rljax_agents/util/optim.py
xpag/agents/rljax_agents/util/preprocess.py
xpag/agents/rljax_agents/util/saving.py
xpag/buffers/__init__.py
xpag/buffers/buffer.py
xpag/buffers/jax_buffer.py
xpag/buffers/rljax_buffer.py
xpag/plotting/__init__.py
xpag/plotting/plotting.py
xpag/samplers/HER.py
xpag/samplers/__init__.py
xpag/samplers/jax_sampler.py
xpag/samplers/sampler.py
xpag/setters/__init__.py
xpag/setters/setter.py
xpag/tools/__init__.py
xpag/tools/eval.py
xpag/tools/learn.py
xpag-0.3.5.dist-info/LICENSE
xpag-0.3.5.dist-info/METADATA
xpag-0.3.5.dist-info/WHEEL
xpag-0.3.5.dist-info/top_level.txt
xpag-0.3.5.dist-info/RECORD
