Metadata-Version: 2.2
Name: xpag
Version: 0.3.5
Summary: xpag: Exploring Agents
Home-page: https://github.com/perrin-isir/xpag
Author: Nicolas Perrin-Gilbert
License: LICENSE
License-File: LICENSE
Requires-Dist: psutil>=5.8.0
Requires-Dist: numpy>=1.21.5
Requires-Dist: matplotlib>=3.1.3
Requires-Dist: joblib>=1.1.0
Requires-Dist: gymnasium>=0.28.1
Requires-Dist: Pillow>=9.0.1
Requires-Dist: ipywidgets>=7.6.5
Requires-Dist: jax>=0.4.8
Requires-Dist: optax>=0.1.2
Requires-Dist: flax>=0.7.2
Requires-Dist: dm-haiku>=0.0.10
Requires-Dist: brax>=0.9.1
Requires-Dist: tensorflow-probability>=0.15.0
Dynamic: author
Dynamic: description
Dynamic: description-content-type
Dynamic: home-page
Dynamic: license
Dynamic: requires-dist
Dynamic: summary
